README
setup.py
pwilang/__init__.py
pwilang/common.py
pwilang/evaluate.py
pwilang/jinjaext.py
pwilang/lineparser.py
pwilang/node.py
pwilang/output.py
pwilang/parse.py
pwilang/parsetab.py
pwilang/preproc.py
pwilang/pwilang
pwilang/pwilang.py
pwilang/watcher.py
pwilang/xml2pwi.py
pwilang/yappsrt.py
pwilang.egg-info/PKG-INFO
pwilang.egg-info/SOURCES.txt
pwilang.egg-info/dependency_links.txt
pwilang.egg-info/requires.txt
pwilang.egg-info/top_level.txt