Metadata-Version: 1.0
Name: pwilang
Version: 0.10.14
Summary: A text processor with its own syntax a little nicer than html that uses jinja for complex text rendering.
Home-page: http://code.google.com/p/pwilang/
Author: Christophe Eymard
Author-email: christophe@ravelsoft.com
License: GPLv3
Keywords: text processor html jinja
Platform: UNKNOWN
Classifier: Development Status :: 4 - Beta
Classifier: Topic :: Utilities
